compas_cloud/__init__.py
compas_cloud/__main__.py
compas_cloud/client_net.py
compas_cloud/client_websockets.py
compas_cloud/install.py
compas_cloud/proxy.py
compas_cloud/server.py
compas_cloud/server_websockets.py
compas_cloud/sessions.py
compas_cloud/speckle/__init__.py
compas_cloud/speckle/data.py
compas_cloud/speckle/speckle.py
compas_cloud-0.4.1.dist-info/LICENSE
compas_cloud-0.4.1.dist-info/METADATA
compas_cloud-0.4.1.dist-info/WHEEL
compas_cloud-0.4.1.dist-info/top_level.txt
compas_cloud-0.4.1.dist-info/RECORD
