Metadata-Version: 2.1
Name: compas-cloud
Version: 0.4.1
Summary: COMPAS package for cloud computing
Home-page: https://github.com/BlockResearchGroup/compas_cloud
Author: Li Chen
Author-email: li.chen@arch.ethz.ch
License: MIT
Keywords: architecture,engineering
Classifier: Development Status :: 4 - Beta
Classifier: Intended Audience :: Developers
Classifier: Topic :: Scientific/Engineering
Classifier: License :: OSI Approved :: MIT License
Classifier: Operating System :: Unix
Classifier: Operating System :: POSIX
Classifier: Operating System :: Microsoft :: Windows
Classifier: Programming Language :: Python
Classifier: Programming Language :: Python :: 2.7
Classifier: Programming Language :: Python :: 3
Classifier: Programming Language :: Python :: 3.6
Classifier: Programming Language :: Python :: 3.7
Classifier: Programming Language :: Python :: 3.8
Classifier: Programming Language :: Python :: 3.9
Classifier: Programming Language :: Python :: Implementation :: CPython
Requires-Python: >=2.7
License-File: LICENSE
Requires-Dist: autobahn (>=20.12.3)
Requires-Dist: websockets (>=9.1)
Requires-Dist: compas
